{
  "main": {
    "id": "4f1db0b80330b026",
    "type": "split",
    "children": [
      {
        "id": "9e1a3dfcc96a1aaf",
        "type": "tabs",
        "children": [
          {
            "id": "9d5d35ff3b5a34ee",
            "type": "leaf",
            "state": {
              "type": "markdown",
              "state": {
                "file": "1. Что такое CI CD.md",
                "mode": "source",
                "source": false
              },
              "icon": "lucide-file",
              "title": "1. Что такое CI CD"
            }
          },
          {
            "id": "34a2644fc4c5deb7",
            "type": "leaf",
            "state": {
              "type": "markdown",
              "state": {
                "file": "2. Как работает GitLab CI.md",
                "mode": "source",
                "source": false
              },
              "icon": "lucide-file",
              "title": "2. Как работает GitLab CI"
            }
          },
          {
            "id": "9542c9efd5d8bd72",
            "type": "leaf",
            "state": {
              "type": "markdown",
              "state": {
                "file": "3. Что такое gitlab runner.md",
                "mode": "source",
                "source": false
              },
              "icon": "lucide-file",
              "title": "3. Что такое gitlab runner"
            }
          }
        ],
        "currentTab": 2
      }
    ],
    "direction": "vertical"
  },
  "left": {
    "id": "ce584a6d6b406347",
    "type": "split",
    "children": [
      {
        "id": "638745e25c7e4a39",
        "type": "tabs",
        "children": [
          {
            "id": "29c4257cdd7beae2",
            "type": "leaf",
            "state": {
              "type": "file-explorer",
              "state": {
                "sortOrder": "alphabetical",
                "autoReveal": false
              },
              "icon": "lucide-folder-closed",
              "title": "Файловый менеджер"
            }
          },
          {
            "id": "4bd834dcabe9fb90",
            "type": "leaf",
            "state": {
              "type": "search",
              "state": {
                "query": "",
                "matchingCase": false,
                "explainSearch": false,
                "collapseAll": false,
                "extraContext": false,
                "sortOrder": "alphabetical"
              },
              "icon": "lucide-search",
              "title": "Поиск"
            }
          },
          {
            "id": "42df0fd0e5242eec",
            "type": "leaf",
            "state": {
              "type": "bookmarks",
              "state": {},
              "icon": "lucide-bookmark",
              "title": "Закладки"
            }
          }
        ]
      }
    ],
    "direction": "horizontal",
    "width": 300
  },
  "right": {
    "id": "d4c66206fafedca4",
    "type": "split",
    "children": [
      {
        "id": "0e50508af49070bf",
        "type": "tabs",
        "children": [
          {
            "id": "96cb174d170ed38d",
            "type": "leaf",
            "state": {
              "type": "backlink",
              "state": {
                "file": "3. Что такое gitlab runner.md",
                "collapseAll": false,
                "extraContext": false,
                "sortOrder": "alphabetical",
                "showSearch": false,
                "searchQuery": "",
                "backlinkCollapsed": false,
                "unlinkedCollapsed": true
              },
              "icon": "links-coming-in",
              "title": "Обратные ссылки для 3. Что такое gitlab runner"
            }
          },
          {
            "id": "ab7bc9e561daa010",
            "type": "leaf",
            "state": {
              "type": "outgoing-link",
              "state": {
                "file": "3. Что такое gitlab runner.md",
                "linksCollapsed": false,
                "unlinkedCollapsed": true
              },
              "icon": "links-going-out",
              "title": "Исходящие ссылки из 3. Что такое gitlab runner"
            }
          },
          {
            "id": "fa21a1793f6bd720",
            "type": "leaf",
            "state": {
              "type": "tag",
              "state": {
                "sortOrder": "frequency",
                "useHierarchy": true,
                "showSearch": false,
                "searchQuery": ""
              },
              "icon": "lucide-tags",
              "title": "Теги"
            }
          },
          {
            "id": "dcf6a2df1e854be9",
            "type": "leaf",
            "state": {
              "type": "all-properties",
              "state": {
                "sortOrder": "frequency",
                "showSearch": false,
                "searchQuery": ""
              },
              "icon": "lucide-archive",
              "title": "Все свойства"
            }
          },
          {
            "id": "0b028522b31d8a5c",
            "type": "leaf",
            "state": {
              "type": "outline",
              "state": {
                "file": "3. Что такое gitlab runner.md",
                "followCursor": false,
                "showSearch": false,
                "searchQuery": ""
              },
              "icon": "lucide-list",
              "title": "Структура 3. Что такое gitlab runner"
            }
          },
          {
            "id": "b038c3dcc988d1ec",
            "type": "leaf",
            "state": {
              "type": "git-view",
              "state": {},
              "icon": "git-pull-request",
              "title": "Source Control"
            }
          }
        ],
        "currentTab": 5
      }
    ],
    "direction": "horizontal",
    "width": 300
  },
  "left-ribbon": {
    "hiddenItems": {
      "switcher:Меню быстрого перехода": false,
      "graph:Граф": false,
      "canvas:Создать новый холст": false,
      "daily-notes:Сегодняшняя заметка": false,
      "templates:Вставить шаблон": false,
      "command-palette:Открыть палитру команд": false,
      "bases:Создать новую базу": false,
      "obsidian-git:Open Git source control": false
    }
  },
  "active": "9542c9efd5d8bd72",
  "lastOpenFiles": [
    "2. Как работает GitLab CI.md",
    "3. Что такое gitlab runner.md",
    "1. Что такое CI CD.md",
    "2. Как работает GitLab CI",
    "CI_CD_what",
    "Добро пожаловать.md"
  ]
}